eigenpuls/__init__.py
eigenpuls/__main__.py
eigenpuls/api.py
eigenpuls/cli.py
eigenpuls/config.py
eigenpuls/integrations/celery.py
eigenpuls/resources/Dockerfile.eigenpuls
eigenpuls/service/__init__.py
eigenpuls/service/base.py
eigenpuls/service/registry.py
eigenpuls/service/models/__init__.py
eigenpuls/service/models/celery.py
eigenpuls/service/models/dns.py
eigenpuls/service/models/http.py
eigenpuls/service/models/postgres.py
eigenpuls/service/models/rabbitmq.py
eigenpuls/service/models/redis.py
eigenpuls-0.1.0.post1.dev41.dist-info/licenses/LICENSE
eigenpuls-0.1.0.post1.dev41.dist-info/METADATA
eigenpuls-0.1.0.post1.dev41.dist-info/WHEEL
eigenpuls-0.1.0.post1.dev41.dist-info/entry_points.txt
eigenpuls-0.1.0.post1.dev41.dist-info/top_level.txt
eigenpuls-0.1.0.post1.dev41.dist-info/RECORD
