Metadata-Version: 2.4
Name: eigenpuls
Version: 0.1.0.post1.dev41
Summary: Container-native autonomous health checker daemon aggregating CLI-based probes with a unified API
Author-email: Eigenpuls Maintainers <maintainers@example.com>
License-Expression: Apache-2.0
Keywords: healthcheck,monitoring,cli,fastapi
Classifier: Programming Language :: Python :: 3
Classifier: Programming Language :: Python :: 3.11
Classifier: Programming Language :: Python :: 3.12
Classifier: Operating System :: POSIX :: Linux
Classifier: Environment :: Console
Classifier: Framework :: FastAPI
Requires-Python: >=3.11
License-File: LICENSE
Requires-Dist: fastapi
Requires-Dist: uvicorn
Requires-Dist: pydantic
Requires-Dist: pydantic-settings
Requires-Dist: PyYAML
Requires-Dist: fire
Requires-Dist: celery
Dynamic: license-file
